agton/jetton/__init__.py
agton/jetton/contracts/__init__.py
agton/jetton/contracts/jetton_master.py
agton/jetton/contracts/jetton_wallet.py
agton/jetton/messages/__init__.py
agton/jetton/messages/burn.py
agton/jetton/messages/transfer.py
agton_jetton-0.2.4.dist-info/licenses/LICENSE
agton_jetton-0.2.4.dist-info/METADATA
agton_jetton-0.2.4.dist-info/WHEEL
agton_jetton-0.2.4.dist-info/top_level.txt
agton_jetton-0.2.4.dist-info/RECORD
